cushead/__init__.py
cushead/exceptions.py
cushead/info.py
cushead/console/__init__.py
cushead/console/console.py
cushead/console/logs.py
cushead/console/arguments/__init__.py
cushead/console/arguments/config.py
cushead/console/arguments/execute.py
cushead/console/arguments/files_creator.py
cushead/console/arguments/setup.py
cushead/console/assets/__init__.py
cushead/console/assets/assets.py
cushead/console/assets/images/favicon_ico_16px.ico
cushead/console/assets/images/favicon_png_2688px.png
cushead/console/assets/images/favicon_svg_scalable.svg
cushead/console/assets/images/preview_png_600px.png
cushead/generator/__init__.py
cushead/generator/config.py
cushead/generator/files.py
cushead/generator/images.py
cushead/generator/templates/__init__.py
cushead/generator/templates/templates.py
cushead/generator/templates/jinja/__init__.py
cushead/generator/templates/jinja/extensions.py
cushead/generator/templates/jinja/filters.py
cushead/generator/templates/jinja/templates/browserconfig.jinja2
cushead/generator/templates/jinja/templates/early_script.jinja2
cushead/generator/templates/jinja/templates/humans.jinja2
cushead/generator/templates/jinja/templates/index.jinja2
cushead/generator/templates/jinja/templates/late_script.jinja2
cushead/generator/templates/jinja/templates/manifest.jinja2
cushead/generator/templates/jinja/templates/opensearch.jinja2
cushead/generator/templates/jinja/templates/robots.jinja2
cushead/generator/templates/jinja/templates/security.jinja2
cushead/generator/templates/jinja/templates/sitemap.jinja2
cushead/generator/templates/jinja/templates/styles.jinja2
cushead/generator/templates/jinja/templates/sw.jinja2
cushead-4.0.5.data/data/LICENSE.md
cushead-4.0.5.data/data/README.md
cushead-4.0.5.data/data/requirements.txt
cushead-4.0.5.data/data/cushead/console/assets/images/favicon_ico_16px.ico
cushead-4.0.5.data/data/cushead/console/assets/images/favicon_png_2688px.png
cushead-4.0.5.data/data/cushead/console/assets/images/favicon_svg_scalable.svg
cushead-4.0.5.dist-info/LICENSE.md
cushead-4.0.5.dist-info/METADATA
cushead-4.0.5.dist-info/WHEEL
cushead-4.0.5.dist-info/entry_points.txt
cushead-4.0.5.dist-info/top_level.txt
cushead-4.0.5.dist-info/RECORD
