Metadata-Version: 2.1
Name: cushead
Version: 4.0.5
Summary: CLI that help you to improve the SEO and UX of your websites.
Home-page: https://github.com/lucasvazq/cushead
Author: Lucas Vazquez
Author-email: lucas5zvazquez@gmail.com
License: MIT
Project-URL: Documentation, https://github.com/lucasvazq/cushead/blob/master/README.md
Project-URL: Source, https://github.com/lucasvazq/cushead
Keywords: SEO,meta-tags,UX,PWA,front-end,favicon,manifest,robots,browserconfig,sitemap,opensearch
Platform: any
Classifier: Development Status :: 5 - Production/Stable
Classifier: Environment :: Console
Classifier: Intended Audience :: Developers
Classifier: License :: OSI Approved :: MIT License
Classifier: Operating System :: OS Independent
Classifier: Programming Language :: Python
Classifier: Programming Language :: Python :: 3
Classifier: Programming Language :: Python :: 3.8
Classifier: Programming Language :: Python :: 3.9
Classifier: Programming Language :: Python :: 3 :: Only
Classifier: Topic :: Utilities
Classifier: Topic :: Software Development
Classifier: Topic :: Software Development :: Code Generators
Classifier: Topic :: Software Development :: Libraries
Classifier: Topic :: Software Development :: Libraries :: Python Modules
Classifier: Topic :: Software Development :: User Interfaces
Requires-Python: >=3.8
Requires-Dist: colorama (==0.4.4)
Requires-Dist: Jinja2 (==2.11.2)
Requires-Dist: Pillow (==8.1.0)
Requires-Dist: python-resize-image (==1.1.19)
Requires-Dist: schema (==0.7.3)
